Workbook

Sheet Supuestos
A1: Taxi-Moto Cusco — Modelo de Unit Economics
A2: Todas las celdas azules son supuestos editables. Cambia cualquiera y el resto del modelo recalcula.
A4: Supuesto | B4: Valor | C4: Nota / fuente
A5: Tarifa por km (S/) | B5: 1.25 | C5: Rango observado en grupo WhatsApp: S/1.00–1.50/km. Punto medio.
A6: Distancia promedio por viaje (km) | B6: 5 | C6: Estimado sobre rutas frecuentes detectadas en la data (San Jerónimo–Centro).
A7: Comisión de la plataforma | B7: 0.18 | C7: Rango sugerido en análisis previo: 15%–20%. Punto medio.
A8: Viajes por conductor activo / día | B8: 8 | C8: Supuesto inicial de piloto — ajustar con data real de las semanas 3-4.
A9: Conductores activos simultáneos (piloto) | B9: 10 | C9: Tamaño de la Fase Concierge (30 días) recomendada.
A10: Días operativos por mes | B10: 26 | C10: Asume descanso semanal 1 día.
A11: Costo de gasolina por km (S/) | B11: 0.35 | C11: Estimado moto lineal 125-150cc, ajustar con precio local de combustible.
A12: Costo fijo mensual de operación (S/) | B12: 800 | C12: WhatsApp Business + hosting + Google Sheet/CRM básico en Fase Concierge.
A14: Nota:
A15: Estas tarifas y comisión reflejan lo que circulaba en el grupo 'Viajes Seguro y Rapido' el 19/7/2026, no un estudio de mercado formal — valídalas en la Fase Concierge antes de fijar precios definitivos.

Sheet Economia por viaje
A1: Economía de un viaje promedio
A3: Concepto | B3: Valor | C3: Fórmula / explicación
A4: Tarifa del viaje (S/) | B4: =Supuestos!B5*Supuestos!B6 -> 6.25 | C4: Tarifa/km × distancia promedio
A5: Comisión de la plataforma (S/) | B5: =B4*Supuestos!B7 -> 1.125 | C5: Tarifa del viaje × % comisión
A6: Neto para el conductor (S/) | B6: =B4-B5 -> 5.125 | C6: Tarifa − comisión
A7: Costo de gasolina del viaje (S/) | B7: =Supuestos!B6*Supuestos!B11 -> 1.75 | C7: Distancia × costo gasolina/km
A8: Margen real del conductor (S/) | B8: =B6-B7 -> 3.375 | C8: Neto − gasolina (antes de desgaste de moto, SOAT, tiempo)
A9: Margen real del conductor (%) | B9: =B8/B4 -> 0.54 | C9: Sobre la tarifa total — ojo si baja de ~50%, el conductor no vuelve

Sheet Proyeccion mensual
A1: Proyección mensual — Fase Concierge (piloto de 30 días)
A3: Métrica | B3: Valor | C3: Fórmula / explicación
A4: Viajes por día (piloto) | B4: =Supuestos!B8*Supuestos!B9 -> 80 | C4: Viajes/conductor/día × conductores activos
A5: Viajes por mes | B5: =B4*Supuestos!B10 -> 2080 | C5: Viajes/día × días operativos/mes
A6: Ingreso bruto transaccionado / mes (S/) | B6: ='Economia por viaje'!B4*B5 -> 13000 | C6: Tarifa promedio × viajes/mes — el GMV de la plataforma
A7: Comisión total / mes (S/) | B7: ='Economia por viaje'!B5*B5 -> 2340 | C7: placeholder
A8: Costos fijos / mes (S/) | B8: =Supuestos!B12 -> 800 | C8: WhatsApp Business, hosting, herramientas del piloto
A9: Utilidad neta del piloto / mes (S/) | B9: =B7-B8 -> 1540 | C9: Comisión total − costos fijos
A10: Ingreso neto total de conductores / mes (S/) | B10: ='Economia por viaje'!B8*B5 -> 7020 | C10: Margen real del conductor × viajes/mes — lo que se llevan los 10 pilotos combinados

Sheet Sensibilidad tarifa-comision
A1: Sensibilidad: comisión por viaje (S/) según tarifa/km y distancia
A2: Cada celda = tarifa/km × distancia × comisión (Supuestos!B7). Cambia la comisión en Supuestos y toda la tabla recalcula.
A4: Distancia (km) \ Tarifa/km | B4: 1 | C4: 1.25 | D4: 1.5
A5: 3 | B5: =B$4*$A5*Supuestos!B7 -> 0.54 | C5: =C$4*$A5*Supuestos!B7 -> 0.675 | D5: =D$4*$A5*Supuestos!B7 -> 0.81
A6: 5 | B6: =B$4*$A6*Supuestos!B7 -> 0.9 | C6: =C$4*$A6*Supuestos!B7 -> 1.125 | D6: =D$4*$A6*Supuestos!B7 -> 1.35
A7: 8 | B7: =B$4*$A7*Supuestos!B7 -> 1.44 | C7: =C$4*$A7*Supuestos!B7 -> 1.8 | D7: =D$4*$A7*Supuestos!B7 -> 2.16
A9: Viajes/día necesarios para S/500 de comisión neta diaria
A10: Comisión promedio por viaje actual (S/) | B10: ='Economia por viaje'!B5 -> 1.125
A11: Viajes/día requeridos | B11: =500/B10 -> 444.44444
